xbsTestTools/__init__.py
xbsTestTools/adb_tools.py
xbsTestTools/format_execution.py
xbsTestTools/method_executor.py
xbsTestTools/operate_controller.py
xbsTestTools/try_error.py
xbsTestTools/log/__init__.py
xbsTestTools/log/colors.py
xbsTestTools/log/jsonlogger.py
xbsTestTools/system_tools/__init__.py
xbsTestTools/system_tools/test_tools.py
xbsTestTools/system_tools/test_ui_tools.py
xbsTestTools/system_tools/buring/download_tool.py
xbsTestTools/system_tools/buring/mtk.py
xbsTestTools/system_tools/buring/qz.py
xbsTestTools/system_tools/buring/zr.py
xbstesttools-0.2.9.dist-info/METADATA
xbstesttools-0.2.9.dist-info/WHEEL
xbstesttools-0.2.9.dist-info/top_level.txt
xbstesttools-0.2.9.dist-info/RECORD
