Metadata-Version: 2.4
Name: xbsTestTools
Version: 0.2.9
Summary: tools
Author-email: 65 <18974710587@163.com>
License: MIT
Classifier: Programming Language :: Python :: 3
Classifier: Operating System :: Microsoft :: Windows
Requires-Python: >=3.10
Requires-Dist: uiautomator2==3.2.9
Requires-Dist: opencv-python==4.11.0.86
Requires-Dist: numpy==2.2.5
Requires-Dist: patool==2.1.1
Requires-Dist: pyserial==3.5
